{"name":"코인 추세추종","strat":"EMA10×30(1h) · ATR×3 손절 · BTC+ETH+SOL","status":"보유 3종목","holding":true,"updated":"2026-07-15 09:54:57 KST","positions":[{"sym":"ETH","qty":"0.081509","avg":2747000,"now":2766000,"stop":2679049.7212690017,"uplPct":0.69},{"sym":"BTC","qty":"0.002383","avg":94030000,"now":95219000,"stop":92617015.77054343,"uplPct":1.26},{"sym":"SOL","qty":"1.972105","avg":113900,"now":114100,"stop":111059.45275056797,"uplPct":0.18}],"focus":{"t":"2026-07-15 00:00","type":"buy","sym":"SOL","price":113900,"qty":"1.972107","amt":224623,"note":"","trigger":"EMA10×30(1h) 골든크로스 진입 · 포지션 = min(30%, 2%÷손절폭)","plan":"청산: 데드크로스 또는 ATR(14)×3 손절선 이탈","metrics":[{"k":"투입 금액","v":"224,623원"},{"k":"총자산","v":"964,513원 (+0.50%)","t":"pos"},{"k":"누적 실현","v":"0원","t":"pos"},{"k":"미실현","v":"4,777원","t":"pos"},{"k":"현금 / 시드","v":"287,130 / 959,737"}]},"past":[{"t":"2026-07-14 23:00","type":"buy","sym":"BTC","price":94030000,"qty":"0.002383","amt":224078,"note":""},{"t":"2026-07-14 22:00","type":"buy","sym":"ETH","price":2747000,"qty":"0.08151","amt":223907,"note":""}]}